zevvle/__init__.py
zevvle/zevvle.py
zevvle_python_sdk-0.0.3.dist-info/LICENSE
zevvle_python_sdk-0.0.3.dist-info/METADATA
zevvle_python_sdk-0.0.3.dist-info/WHEEL
zevvle_python_sdk-0.0.3.dist-info/top_level.txt
zevvle_python_sdk-0.0.3.dist-info/RECORD
