Metadata-Version: 2.1
Name: zevvle-python-sdk
Version: 0.0.3
Summary: The unofficial Python library and SDK for the Zevvle API. 
Home-page: https://github.com/crablab/zevvle_python_sdk
Author: Hugh Wells
Author-email: hugh@crablab.co.uk
License: UNKNOWN
Platform: UNKNOWN
Classifier: Programming Language :: Python :: 3
Classifier: License :: OSI Approved :: MIT License
Classifier: Operating System :: OS Independent
Requires-Python: >=3.8
